admin_extra_urls/__init__.py
admin_extra_urls/extras.py
admin_extra_urls/mixins.py
admin_extra_urls/site.py
admin_extra_urls/templates/admin_extra_urls/change_form.html
admin_extra_urls/templates/admin_extra_urls/change_list.html
admin_extra_urls/templates/admin_extra_urls/confirm.html
admin_extra_urls/templates/admin_extra_urls/grappelli/change_form.html
admin_extra_urls/templates/admin_extra_urls/grappelli/change_list.html
admin_extra_urls/templates/admin_extra_urls/grappelli/includes/change_form_buttons.html
admin_extra_urls/templates/admin_extra_urls/grappelli/includes/change_list_buttons.html
admin_extra_urls/templates/admin_extra_urls/includes/change_form_buttons.html
admin_extra_urls/templates/admin_extra_urls/includes/change_list_buttons.html
admin_extra_urls/templatetags/__init__.py
admin_extra_urls/templatetags/extra_urls.py
admin_extra_urls-2.2.0.dist-info/LICENSE
admin_extra_urls-2.2.0.dist-info/METADATA
admin_extra_urls-2.2.0.dist-info/WHEEL
admin_extra_urls-2.2.0.dist-info/top_level.txt
admin_extra_urls-2.2.0.dist-info/RECORD
