Metadata-Version: 2.1
Name: admin-extra-urls
Version: 2.2.0
Summary: Django mixin to easily add urls to any ModelAdmin
Home-page: https://github.com/saxix/django-admin-extra-urls
License: UNKNOWN
Download-URL: https://pypi.python.org/pypi/admin-extra-urls
Platform: linux
Classifier: Environment :: Web Environment
Classifier: Operating System :: OS Independent
Classifier: Framework :: Django
Classifier: Framework :: Django :: 2.0
Classifier: Framework :: Django :: 2.1
Classifier: Framework :: Django :: 2.2
Classifier: Framework :: Django :: 3.0
Classifier: License :: OSI Approved :: BSD License
Classifier: Programming Language :: Python :: 3
Classifier: Programming Language :: Python :: 3.6
Classifier: Programming Language :: Python :: 3.7
Classifier: Programming Language :: Python :: 3.8
Classifier: Topic :: Software Development :: Libraries :: Application Frameworks
Classifier: Topic :: Software Development :: Libraries :: Python Modules
Classifier: Intended Audience :: Developers
Provides-Extra: dev
Requires-Dist: autopep8 ; extra == 'dev'
Requires-Dist: check-manifest ; extra == 'dev'
Requires-Dist: flake8 ; extra == 'dev'
Requires-Dist: pep8 ; extra == 'dev'
Requires-Dist: readme ; extra == 'dev'
Requires-Dist: wheel ; extra == 'dev'
Requires-Dist: coverage ; extra == 'dev'
Requires-Dist: factory-boy ; extra == 'dev'
Requires-Dist: django-webtest ; extra == 'dev'
Requires-Dist: pdbpp ; extra == 'dev'
Requires-Dist: pyquery ; extra == 'dev'
Requires-Dist: pytest ; extra == 'dev'
Requires-Dist: pytest-cov ; extra == 'dev'
Requires-Dist: pytest-django ; extra == 'dev'
Requires-Dist: pytest-echo ; extra == 'dev'
Requires-Dist: pytest-pythonpath ; extra == 'dev'
Requires-Dist: tox (>=2.3) ; extra == 'dev'
Provides-Extra: tests
Requires-Dist: coverage ; extra == 'tests'
Requires-Dist: factory-boy ; extra == 'tests'
Requires-Dist: django-webtest ; extra == 'tests'
Requires-Dist: pdbpp ; extra == 'tests'
Requires-Dist: pyquery ; extra == 'tests'
Requires-Dist: pytest ; extra == 'tests'
Requires-Dist: pytest-cov ; extra == 'tests'
Requires-Dist: pytest-django ; extra == 'tests'
Requires-Dist: pytest-echo ; extra == 'tests'
Requires-Dist: pytest-pythonpath ; extra == 'tests'
Requires-Dist: tox (>=2.3) ; extra == 'tests'
Requires-Dist: wheel ; extra == 'tests'
